mhi/help/__init__.py
mhi/help/__main__.py
mhi/help/py.typed
mhi/help/html/genindex.html
mhi/help/html/index.html
mhi/help/html/packages.html
mhi/help/html/search.html
mhi/help/html/searchindex.js
mhi/help/html/_static/basic.css
mhi/help/html/_static/check-solid.svg
mhi/help/html/_static/clipboard.min.js
mhi/help/html/_static/copy-button.svg
mhi/help/html/_static/copybutton.css
mhi/help/html/_static/copybutton.js
mhi/help/html/_static/copybutton_funcs.js
mhi/help/html/_static/custom.css
mhi/help/html/_static/doctools.js
mhi/help/html/_static/documentation_options.js
mhi/help/html/_static/file.png
mhi/help/html/_static/language_data.js
mhi/help/html/_static/mhi_logo.svg
mhi/help/html/_static/minus.png
mhi/help/html/_static/plus.png
mhi/help/html/_static/pscad_logo.svg
mhi/help/html/_static/pygments.css
mhi/help/html/_static/searchtools.js
mhi/help/html/_static/sphinx_highlight.js
mhi/help/html/_static/toggle_code_output.js
mhi/help/html/_static/webpack-macros.html
mhi/help/html/_static/scripts/bootstrap.js
mhi/help/html/_static/scripts/bootstrap.js.LICENSE.txt
mhi/help/html/_static/scripts/bootstrap.js.map
mhi/help/html/_static/scripts/fontawesome.js
mhi/help/html/_static/scripts/fontawesome.js.LICENSE.txt
mhi/help/html/_static/scripts/fontawesome.js.map
mhi/help/html/_static/scripts/pydata-sphinx-theme.js
mhi/help/html/_static/scripts/pydata-sphinx-theme.js.map
mhi/help/html/_static/styles/pydata-sphinx-theme.css
mhi/help/html/_static/styles/pydata-sphinx-theme.css.map
mhi/help/html/_static/styles/theme.css
mhi/help/html/_static/vendor/fontawesome/webfonts/fa-brands-400.ttf
mhi/help/html/_static/vendor/fontawesome/webfonts/fa-brands-400.woff2
mhi/help/html/_static/vendor/fontawesome/webfonts/fa-regular-400.ttf
mhi/help/html/_static/vendor/fontawesome/webfonts/fa-regular-400.woff2
mhi/help/html/_static/vendor/fontawesome/webfonts/fa-solid-900.ttf
mhi/help/html/_static/vendor/fontawesome/webfonts/fa-solid-900.woff2
mhi_help-1.0.0.dist-info/licenses/LICENSE
mhi_help-1.0.0.dist-info/METADATA
mhi_help-1.0.0.dist-info/WHEEL
mhi_help-1.0.0.dist-info/top_level.txt
mhi_help-1.0.0.dist-info/RECORD
